isaaclab/__init__.py
isaaclab/__main__.py
isaaclab/apps/isaaclab.python.headless.kit
isaaclab/apps/isaaclab.python.headless.rendering.kit
isaaclab/apps/isaaclab.python.kit
isaaclab/apps/isaaclab.python.rendering.kit
isaaclab/apps/isaaclab.python.xr.openxr.headless.kit
isaaclab/apps/isaaclab.python.xr.openxr.kit
isaaclab/apps/isaacsim_4_5/extension.toml
isaaclab/apps/isaacsim_4_5/isaaclab.python.headless.kit
isaaclab/apps/isaacsim_4_5/isaaclab.python.headless.rendering.kit
isaaclab/apps/isaacsim_4_5/isaaclab.python.kit
isaaclab/apps/isaacsim_4_5/isaaclab.python.rendering.kit
isaaclab/apps/isaacsim_4_5/isaaclab.python.xr.openxr.headless.kit
isaaclab/apps/isaacsim_4_5/isaaclab.python.xr.openxr.kit
isaaclab/apps/isaacsim_4_5/rendering_modes/balanced.kit
isaaclab/apps/isaacsim_4_5/rendering_modes/performance.kit
isaaclab/apps/isaacsim_4_5/rendering_modes/quality.kit
isaaclab/apps/isaacsim_4_5/rendering_modes/xr.kit
isaaclab/apps/rendering_modes/balanced.kit
isaaclab/apps/rendering_modes/extension.toml
isaaclab/apps/rendering_modes/performance.kit
isaaclab/apps/rendering_modes/quality.kit
isaaclab/source/isaaclab/pyproject.toml
isaaclab/source/isaaclab/setup.py
isaaclab/source/isaaclab/config/extension.toml
isaaclab/source/isaaclab/docs/CHANGELOG.rst
isaaclab/source/isaaclab/docs/README.md
isaaclab/source/isaaclab/isaaclab/__init__.py
isaaclab/source/isaaclab/isaaclab/actuators/__init__.py
isaaclab/source/isaaclab/isaaclab/actuators/actuator_base.py
isaaclab/source/isaaclab/isaaclab/actuators/actuator_cfg.py
isaaclab/source/isaaclab/isaaclab/actuators/actuator_net.py
isaaclab/source/isaaclab/isaaclab/actuators/actuator_pd.py
isaaclab/source/isaaclab/isaaclab/app/__init__.py
isaaclab/source/isaaclab/isaaclab/app/app_launcher.py
isaaclab/source/isaaclab/isaaclab/assets/__init__.py
isaaclab/source/isaaclab/isaaclab/assets/asset_base.py
isaaclab/source/isaaclab/isaaclab/assets/asset_base_cfg.py
isaaclab/source/isaaclab/isaaclab/assets/articulation/__init__.py
isaaclab-2.3.1.dist-info/METADATA
isaaclab-2.3.1.dist-info/WHEEL
isaaclab-2.3.1.dist-info/entry_points.txt
isaaclab-2.3.1.dist-info/top_level.txt
isaaclab-2.3.1.dist-info/RECORD
