Metadata-Version: 2.4
Name: isaaclab
Version: 2.3.1
Summary: Isaac Lab
Author: Isaac Lab team
License: NVIDIA Proprietary Software
Project-URL: Home page, https://developer.nvidia.com/isaac/lab
Project-URL: Documentation, https://isaac-sim.github.io/IsaacLab/
Project-URL: Forum, https://forums.developer.nvidia.com/c/omniverse/simulation/69
Keywords: nvidia,omniverse,isaacsim,isaaclab
Classifier: Programming Language :: Python :: 3
Classifier: Programming Language :: Python :: 3.11
Classifier: License :: Other/Proprietary License
Requires-Python: ==3.11.*
Requires-Dist: numpy<2
Requires-Dist: torch>=2.7
Requires-Dist: onnx>=1.18.0
Requires-Dist: prettytable==3.3.0
Requires-Dist: toml
Requires-Dist: hidapi==0.14.0.post2
Requires-Dist: gymnasium==1.2.0
Requires-Dist: trimesh
Requires-Dist: pyglet<2
Requires-Dist: transformers
Requires-Dist: einops
Requires-Dist: warp-lang
Requires-Dist: pillow==11.3.0
Requires-Dist: starlette==0.45.3
Requires-Dist: pytest
Requires-Dist: pytest-mock
Requires-Dist: junitparser
Requires-Dist: flatdict==4.0.1
Requires-Dist: flaky
Requires-Dist: numpy<2
Requires-Dist: torch>=2.7
Requires-Dist: torchvision>=0.14.1
Requires-Dist: protobuf!=5.26.0,>=4.25.8
Requires-Dist: hydra-core
Requires-Dist: h5py
Requires-Dist: tensorboard
Requires-Dist: moviepy
Requires-Dist: pillow==11.3.0
Requires-Dist: packaging<24
Requires-Dist: numpy<2
Requires-Dist: torch>=2.7
Requires-Dist: torchvision>=0.14.1
Requires-Dist: protobuf!=5.26.0,>=4.25.8
Requires-Dist: tensorboard
Requires-Dist: numba
Provides-Extra: isaacsim
Requires-Dist: isaacsim[all,extscache]==5.1.0.*; extra == "isaacsim"
Provides-Extra: sb3
Requires-Dist: stable-baselines3>=2.6; extra == "sb3"
Requires-Dist: tqdm; extra == "sb3"
Requires-Dist: rich; extra == "sb3"
Provides-Extra: skrl
Requires-Dist: skrl>=1.4.3; extra == "skrl"
Provides-Extra: rsl-rl
Requires-Dist: rsl-rl-lib==3.0.1; extra == "rsl-rl"
Requires-Dist: onnxscript>=0.5; extra == "rsl-rl"
Provides-Extra: rsl-rl
Requires-Dist: rsl-rl-lib==3.0.1; extra == "rsl-rl"
Requires-Dist: onnxscript>=0.5; extra == "rsl-rl"
Provides-Extra: all
Requires-Dist: stable-baselines3>=2.6; extra == "all"
Requires-Dist: tqdm; extra == "all"
Requires-Dist: rich; extra == "all"
Requires-Dist: skrl>=1.4.3; extra == "all"
Requires-Dist: rsl-rl-lib==3.0.1; extra == "all"
Requires-Dist: onnxscript>=0.5; extra == "all"
